ndl_code-0.1.0.dist-info/licenses/LICENSE.txt
ndl_codes/__init__.py
ndl_codes/lab_10.py
ndl_codes/lab_11.py
ndl_codes/lab_12a.py
ndl_codes/lab_12b.py
ndl_codes/lab_12c.py
ndl_codes/lab_1b.py
ndl_codes/lab_1b_part2.py
ndl_codes/lab_2.py
ndl_codes/lab_3a.py
ndl_codes/lab_3a_part2.py
ndl_codes/lab_3b.py
ndl_codes/lab_4.py
ndl_codes/lab_5.py
ndl_codes/lab_6a.py
ndl_codes/lab_6b.py
ndl_codes/lab_7a.py
ndl_codes/lab_7b.py
ndl_codes/lab_8.py
ndl_codes/lab_9.py
ndl_code-0.1.0.dist-info/METADATA
ndl_code-0.1.0.dist-info/WHEEL
ndl_code-0.1.0.dist-info/top_level.txt
ndl_code-0.1.0.dist-info/RECORD
